[
  {
    "titulo": {
      "title": "fgfggfb",
      "price": "fgfgb",
      "thumbnail": "fgfgbfbg"
    },
    "id": 1
  },
  {
    "titulo": {
      "title": "fgfggfb",
      "price": "fgfgb",
      "thumbnail": "fgfgbfbg"
    },
    "id": 2
  },
  {
    "titulo": {
      "title": "dsds",
      "price": "sdsd",
      "thumbnail": "hola"
    },
    "id": 3
  },
  {
    "titulo": {
      "title": "sadas",
      "price": "sadasd",
      "thumbnail": "asdas"
    },
    "id": 4
  },
  {
    "titulo": {
      "title": "sadas",
      "price": "sadasd",
      "thumbnail": "asdas"
    },
    "id": 5
  },
  {
    "titulo": {
      "title": "asdad",
      "price": "asdas",
      "thumbnail": "asda"
    },
    "id": 6
  },
  {
    "titulo": {
      "title": "asdad",
      "price": "asdas",
      "thumbnail": "asda"
    },
    "id": 7
  },
  {
    "titulo": {
      "title": "sdfsdf",
      "price": "sd",
      "thumbnail": "dfdff"
    },
    "id": 8
  },
  {
    "titulo": {
      "title": "sdfsdf",
      "price": "sd",
      "thumbnail": "dfdff"
    },
    "id": 9
  },
  {
    "titulo": {
      "title": "sa",
      "price": "sa",
      "thumbnail": "sa"
    },
    "id": 10
  },
  {
    "titulo": {
      "title": "sa",
      "price": "sa",
      "thumbnail": "sa"
    },
    "id": 11
  },
  {
    "titulo": {
      "title": "sad",
      "price": "sdasd",
      "thumbnail": "sdas"
    },
    "id": 12
  },
  {
    "titulo": {
      "title": "sad",
      "price": "sdasd",
      "thumbnail": "sdas"
    },
    "id": 13
  },
  {
    "titulo": {
      "title": "sf",
      "price": "sdf",
      "thumbnail": "sdf"
    },
    "id": 14
  },
  {
    "titulo": {
      "title": "sf",
      "price": "sdf",
      "thumbnail": "sdf"
    },
    "id": 15
  },
  {
    "titulo": {
      "title": "fd",
      "price": "fd",
      "thumbnail": "fd"
    },
    "id": 16
  },
  {
    "titulo": {
      "title": "d",
      "price": "1",
      "thumbnail": "fsdfds"
    },
    "id": 17
  },
  {
    "titulo": {
      "title": "d",
      "price": "1",
      "thumbnail": "fsdfds"
    },
    "id": 18
  },
  {
    "titulo": {
      "title": "d",
      "price": "d",
      "thumbnail": "d"
    },
    "id": 19
  },
  {
    "titulo": {
      "title": "s",
      "price": "s",
      "thumbnail": "s"
    },
    "id": 20
  },
  {
    "titulo": {
      "title": "s",
      "price": "s",
      "thumbnail": "s"
    },
    "id": 21
  },
  {
    "titulo": {
      "title": "as",
      "price": "asa",
      "thumbnail": "asa"
    },
    "id": 22
  },
  {
    "titulo": {
      "title": "as",
      "price": "asa",
      "thumbnail": "asa"
    },
    "id": 23
  },
  {
    "titulo": {
      "title": "sa",
      "price": "asa",
      "thumbnail": "asa"
    },
    "id": 24
  },
  {
    "titulo": {
      "title": "sa",
      "price": "asa",
      "thumbnail": "asa"
    },
    "id": 25
  },
  {
    "titulo": {
      "title": "sa",
      "price": "sa",
      "thumbnail": "sa"
    },
    "id": 26
  },
  {
    "titulo": {
      "title": "sa",
      "price": "sa",
      "thumbnail": "sa"
    },
    "id": 27
  },
  {
    "titulo": {
      "title": "ssd",
      "price": "sda",
      "thumbnail": "sada"
    },
    "id": 28
  },
  {
    "titulo": {
      "title": "sa",
      "price": "sa",
      "thumbnail": "sa"
    },
    "id": 29
  },
  {
    "titulo": {
      "title": "sa",
      "price": "sa",
      "thumbnail": "sa"
    },
    "id": 30
  },
  {
    "titulo": {
      "title": "sa",
      "price": "sa",
      "thumbnail": "sa"
    },
    "id": 31
  }
]